[{"_id":"WzTvyyRGkp2pf79aQ","name":"Aanbouw bouwen","urns":["OefenAanbouwOfBijgebouwBouwen"]},{"_id":"qPcaiw4H5vXkZgfFp","name":"Aanbouw monument","urns":[]},{"_id":"MtNRm9GhSkdPavHJa","name":"Aanbouw gebruiken","urns":[]},{"_id":"mpQ4YsJWhRTzxkM8n","urns":["TankstationStartenOfVeranderen"],"name":"Bouwen van bijbehorend bouwwerk"},{"_id":"enavtgGrJEWwT5RGJ","urns":[],"name":"Dakkapel bouwen OLD"},{"_id":"yim42gLF6qjRXeD6D","urns":[],"name":"Simpele Demo Checker voor in de Frontend"},{"_id":"bmf5XsTrZpgTkbJoP","urns":["TankstationStartenOfVeranderen"],"name":"Eendaags evenement"},{"_id":"5CJrbgbWZP6uZsouY","urns":[],"name":"Kozijn plaatsen"},{"_id":"Xm2WwYeGkNN9w6rgQ","urns":[],"name":"Kozijn plaatsen in een monument"},{"_id":"skPG9qqTqWyX9tSY7","urns":["OefenHekOfSchuttingPlaatsenVeranderenOfVerwijderen"],"name":"Zonnepaneel en zonneboiler bouwen"},{"_id":"TRhZrFexMjBW42Ky6","urns":["OefenHekOfSchuttingPlaatsenVeranderenOfVerwijderen"],"name":"Zonnepaneel en zonneboiler monument"},{"_id":"WKPxKx4YBJ5fqYSni","urns":["OefenDakkapelPlaatsenOfVeranderen"],"name":"Dakkapel monument"},{"_id":"6nb6FYuztEENADbmS","urns":[],"name":"Kennis Omgevingswet"},{"_id":"LhnXDJZDmM7snACGX","urns":[],"name":"Boom kappen of snoeien"},{"_id":"Aa2EX3YprpZQ65non","urns":["OefenDakkapelPlaatsenOfVeranderen"],"name":"Dakkapel bouwen\t"},{"_id":"hMwHKR7Wz4FP8Dm4x","urns":["WasstraatOfWasplaatsVoorAutoSBussenTreinenEnTrams"],"name":"Het wijzigen van een monument bij een dakraam"},{"_id":"dRy4PfDs7jQPc9gMG","urns":["WasstraatOfWasplaatsVoorAutoSBussenTreinenEnTrams"],"name":"Dakraam bouwen"},{"_id":"TuP6ido9xpJSSxjLi","urns":[],"name":"Zonwering, rolhek, luik of rolluik bouwen"},{"_id":"AkxinYRNNo679qi6T","urns":[],"name":"Zonwering, rolhek, luik of rolluik monument"},{"_id":"oeDaandaPbYNMgh4J","urns":["OefenUitvoerenVanEenWerk"],"name":"aansluit digikoppeling test"},{"_id":"37mYBbnidDABYfjiM","urns":["SteigerVlonderOfAanmeervoorzieningPlaatsenAanpassenOnderhoudenOfVerwijderen"],"name":"Test outcomes/conclusions"},{"_id":"7vjj2nkFqxp8uQnqS","urns":["OefenUitvoerenVanEenWerk"],"name":"Afmonteren voor DSO V2"},{"_id":"X7LG33jf2M2Szav98","urns":[],"name":"Ontheffing Vrachtauto, bijzonder voertuig en Ondeelbare lading"}]
