{
  "permits": [
    {
      "version": 9,
      "name": "Conclusie Kozijn plaatsen in een monument",
      "questions": [
        {
          "text": "Is het gebouw een monument?",
          "description": "Het rijk of de gemeente kan een gebouw als monument aanwijzen.",
          "autofill": "monumentList",
          "options": [
            "Rijksmonument",
            "Gemeentelijk monument",
            "Geen monument"
          ],
          "type": "string",
          "prio": 10,
          "uuid": "kozijn-monument",
          "id": "fd9899df974598b284692646da0ff8b5"
        },
        {
          "text": "Gaat u een kozijn plaatsen of vernieuwen?",
          "options": [
            "Ik ga een nieuw kozijn plaatsen op een plek waar er eerst geen was.",
            "Ik ga een kozijn plaatsen of vernieuwen op een plek waar er eerst al een was."
          ],
          "type": "string",
          "prio": 20,
          "uuid": "kozijn-onderhoud1",
          "id": "37be1589dc9eb87496f29bfe5ea054d2"
        },
        {
          "text": "U gaat een kozijn plaatsen of vernieuwen op een plek waar er eerst al een was. Verandert de vorm, de grootte of het profiel? Of verandert de kleur of het materiaal?",
          "options": [
            "Ja, het kozijn verandert.",
            "Nee, de vorm, de grootte en het profiel veranderen niet. Ook kleur en materiaal veranderen niet."
          ],
          "type": "string",
          "prio": 30,
          "uuid": "kozijn-onderhoud2",
          "id": "8cca423541aeca3590b1b130ce850341"
        }
      ],
      "decisions": {
        "62afe1cd6ab025646855fc78064a6290": {
          "requiredInputs": [
            "fd9899df974598b284692646da0ff8b5",
            "37be1589dc9eb87496f29bfe5ea054d2"
          ],
          "decisionTable": {
            "rules": [
              {
                "inputs": [
                  "\"Rijksmonument\"",
                  "\"Ik ga een nieuw kozijn plaatsen op een plek waar er eerst geen was.\""
                ],
                "output": "\"Vergunningplicht\""
              },
              {
                "inputs": [
                  "\"Gemeentelijk monument\"",
                  "\"Ik ga een nieuw kozijn plaatsen op een plek waar er eerst geen was.\""
                ],
                "output": "\"Vergunningplicht\""
              },
              {
                "inputs": ["\"Geen monument\"", "-"],
                "output": "\"no hit\""
              },
              {
                "inputs": [
                  "-",
                  "\"Ik ga een kozijn plaatsen of vernieuwen op een plek waar er eerst al een was.\""
                ],
                "output": "\"no hit\""
              }
            ]
          }
        },
        "725dfa3809ff1f9e0a7942b1827d41c8": {
          "requiredInputs": [
            "fd9899df974598b284692646da0ff8b5",
            "37be1589dc9eb87496f29bfe5ea054d2",
            "8cca423541aeca3590b1b130ce850341"
          ],
          "decisionTable": {
            "rules": [
              {
                "inputs": [
                  "\"Rijksmonument\"",
                  "\"Ik ga een kozijn plaatsen of vernieuwen op een plek waar er eerst al een was.\"",
                  "\"Ja, het kozijn verandert.\""
                ],
                "output": "\"Vergunningplicht\""
              },
              {
                "inputs": [
                  "\"Gemeentelijk monument\"",
                  "\"Ik ga een kozijn plaatsen of vernieuwen op een plek waar er eerst al een was.\"",
                  "\"Ja, het kozijn verandert.\""
                ],
                "output": "\"Vergunningplicht\""
              },
              {
                "inputs": ["\"Geen monument\"", "-", "-"],
                "output": "\"no hit\""
              },
              {
                "inputs": [
                  "-",
                  "\"Ik ga een nieuw kozijn plaatsen op een plek waar er eerst geen was.\"",
                  "-"
                ],
                "output": "\"no hit\""
              },
              {
                "inputs": [
                  "-",
                  "-",
                  "\"Nee, de vorm, de grootte en het profiel veranderen niet. Ook kleur en materiaal veranderen niet.\""
                ],
                "output": "\"no hit\""
              }
            ]
          }
        },
        "dummy": {
          "requiredDecisions": [
            "62afe1cd6ab025646855fc78064a6290",
            "725dfa3809ff1f9e0a7942b1827d41c8"
          ],
          "decisionTable": {
            "rules": [
              {
                "inputs": ["\"Vergunningplicht\"", "-"],
                "output": "\"Vergunningplicht\"",
                "description": "U wilt een kozijn plaatsen in een monument. Daarom hebt u waarschijnlijk een vergunning nodig. U vraagt deze vergunning aan bij het landelijke omgevingsloket. Klik hiervoor op onderstaande knop."
              },
              {
                "inputs": ["-", "\"Vergunningplicht\""],
                "output": "\"Vergunningplicht\"",
                "description": "U wilt een kozijn plaatsen in een monument. Daarom hebt u waarschijnlijk een vergunning nodig. U vraagt deze vergunning aan bij het landelijke omgevingsloket. Klik hiervoor op onderstaande knop."
              },
              {
                "inputs": ["\"no hit\"", "\"no hit\""],
                "output": "\"Toestemmingsvrij\"",
                "description": "U hebt geen vergunning nodig voor het onderdeel monument."
              }
            ]
          }
        }
      }
    },
    {
      "version": 28,
      "name": "Conclusie Kozijn plaatsen",
      "questions": [
        {
          "text": "Is het gebouw een monument?",
          "description": "Het rijk of de gemeente kan een gebouw als monument aanwijzen.",
          "autofill": "monumentList",
          "options": [
            "Rijksmonument",
            "Gemeentelijk monument",
            "Geen monument"
          ],
          "type": "string",
          "prio": 10010,
          "uuid": "kozijn-monument",
          "id": "1eadce5a190e452699c0b7620386c2ac"
        },
        {
          "text": "Gaat u een kozijn plaatsen of vernieuwen?",
          "options": [
            "Ik ga een nieuw kozijn plaatsen op een plek waar er eerst geen was.",
            "Ik ga een kozijn plaatsen of vernieuwen op een plek waar er eerst al een was."
          ],
          "type": "string",
          "prio": 10020,
          "uuid": "kozijn-onderhoud1",
          "id": "25cb5125db81edc8c6404ce76e9b62c9"
        },
        {
          "text": "U gaat een kozijn plaatsen of vernieuwen op een plek waar er eerst al een was. Verandert de vorm, de grootte of het profiel? Of verandert de kleur of het materiaal?",
          "options": [
            "Ja, het kozijn verandert.",
            "Nee, de vorm, de grootte en het profiel veranderen niet. Ook kleur en materiaal veranderen niet."
          ],
          "type": "string",
          "prio": 10030,
          "uuid": "kozijn-onderhoud2",
          "id": "1f01e0c37fd56dc8800380fd77541dcf"
        },
        {
          "text": "Gaat u een kozijn plaatsen of vernieuwen?",
          "options": [
            "Ik ga een nieuw kozijn plaatsen op een plek waar er eerst geen was.",
            "Ik ga een kozijn plaatsen of vernieuwen op een plek waar er eerst al een was."
          ],
          "type": "string",
          "prio": 10040,
          "id": "ab7ad575972c1cb19bffde2977c00c2b"
        },
        {
          "text": "U gaat een kozijn plaatsen of vernieuwen op een plek waar er eerst al een was. Verandert de vorm, de grootte of het profiel?",
          "options": [
            "Ja, de vorm, de grootte of het profiel verandert.",
            "Nee, de vorm, de grootte en het profiel veranderen niet."
          ],
          "type": "string",
          "prio": 10050,
          "id": "8b312e9536ed39e46c3c0ea6248cb709"
        },
        {
          "text": "Ligt het gebouw in een beschermd stads- of dorpsgezicht?",
          "description": "We kunnen op dit moment deze vraag niet automatisch beantwoorden. Bekijk [op de kaart](https://www.amsterdam.nl/kunst-cultuur/monumenten/wet-regelgeving/beschermde-stads/) of het gebouw in een beschermd stads- of dorpsgezicht ligt. En of het om een rijksbeschermd of gemeentelijk beschermd stads- of dorpsgezicht gaat.\n\nRijksbeschermde stads- of dorpsgezichten zijn op de kaart blauw gekleurd. De gemeentelijk beschermde stads- of dorpsgezichten zijn rood of geel.",
          "autofill": "cityScapeForBuilding",
          "options": [
            "Ja, het gebouw ligt in een rijksbeschermd stads- of dorpsgezicht.",
            "Ja, het gebouw ligt in een gemeentelijk beschermd stads- of dorpsgezicht.",
            "Nee, het gebouw ligt niet in een beschermd stads- of dorpsgezicht."
          ],
          "type": "string",
          "prio": 10060,
          "id": "e3c7868ee0fd5e496855f3462fc029f7"
        },
        {
          "text": "Gaat u het kozijn plaatsen in een hoofdgebouw of in een aanbouw, uitbouw of bijgebouw?",
          "description": "Een hoofdgebouw is het belangrijkste gebouw op het terrein, vaak is dat de woning.\n\nGaat u een kozijn plaatsen in een hoofdgebouw en in een aanbouw, uitbouw of bijgebouw? Doe dan een vergunningcheck voor het hoofdgebouw en een vergunningcheck voor de aanbouw, de uitbouw of het bijgebouw.",
          "options": [
            "In een hoofdgebouw",
            "In een aanbouw, uitbouw of bijgebouw"
          ],
          "type": "string",
          "prio": 10070,
          "id": "00e898edcd392d99fd044cc7556d1130"
        },
        {
          "text": "Aan welke kant van het hoofdgebouw gaat u een kozijn plaatsen?",
          "description": "![Kozijnen in de voorkant van het gebouw.](https://sttr-files.flolegal.app/00000001002564440000/kozijn_kant_voorkant_01.png \"Voorkant\")\n\n![Kozijnen in de zijkant van het gebouw.](https://sttr-files.flolegal.app/00000001002564440000/kozijn_kant_zijkant_01.png \"Zijkant\")\n\n![Kozijnen in de achterkant van het gebouw.](https://sttr-files.flolegal.app/00000001002564440000/kozijn_kant_achterkant_01.png \"Achterkant\")\n\nDe regels zijn verschillend voor de voorkant, zijkant en achterkant. Gaat u aan meer dan 1 kant een kozijn plaatsen? Doe voor iedere kant een vergunningcheck.",
          "options": ["Voorkant", "Zijkant", "Achterkant"],
          "type": "string",
          "prio": 10080,
          "id": "d49ca838fb038c0ead04dbf81fef24c5"
        },
        {
          "text": "U gaat een kozijn plaatsen aan de zijkant van het gebouw. Ligt die kant aan een straat, fietspad of voetpad waar iedereen mag komen?",
          "description": "![Een kozijn in de zijgevel. De zijgevel ligt aan een weg.](https://sttr-files.flolegal.app/00000001002564440000/OTG_Zijkant-weg_01.png \"Zijkant aan een straat, fietspad of voetpad.\")\n\nAls u naast het gebouw een tuin hebt en die ligt aan een straat, fietspad of voetpad, beantwoordt u de vraag met ‘ja’.",
          "type": "boolean",
          "prio": 10090,
          "id": "c13ff0b1421c4e4c179244d584ae4c1f"
        },
        {
          "text": "U gaat een kozijn plaatsen aan de zijkant van het gebouw. Ligt die kant aan een gracht, kanaal of een ander vaarwater waar iedereen mag komen?",
          "description": "![Een kozijn in de zijgevel. De zijgevel ligt aan vaarwater.](https://sttr-files.flolegal.app/00000001002564440000/OTG_Zijkant-water_01.png \"Zijkant aan een gracht, kanaal of ander vaarwater.\")\n\nAls u naast het gebouw een tuin hebt en die ligt aan een gracht, kanaal of ander vaarwater, beantwoordt u de vraag met ‘ja’.",
          "type": "boolean",
          "prio": 10100,
          "id": "34fc5a5b84202066fa3e29c6946939c1"
        },
        {
          "text": "U gaat een kozijn plaatsen aan de zijkant van het gebouw. Ligt die kant aan een plein, park of parkeerplaats waar iedereen mag komen?",
          "description": "![Een kozijn in de zijgevel. De zijgevel ligt aan een plantsoen.](https://sttr-files.flolegal.app/00000001002564440000/OTG_Zijkant-plantsoen_01.png \"Zijkant aan een plein, park of parkeerplaats.\")\n\nAls u naast het gebouw een tuin hebt en die ligt aan een plein, park of parkeerplaats, beantwoordt u de vraag met ‘ja’.",
          "type": "boolean",
          "prio": 10110,
          "id": "3fe613f807f0a5ee93b535b6ac05f880"
        },
        {
          "text": "U gaat een kozijn plaatsen aan de achterkant van het gebouw. Ligt die kant aan een straat, fietspad of voetpad waar iedereen mag komen?",
          "description": "![Kozijnen in de achtergevel. De achtergevel ligt aan een weg.](https://sttr-files.flolegal.app/00000001002564440000/OTG_Achterkant-weg_01.png \"Achterkant aan een straat, fietspad of voetpad.\")\n\nAls er direct achter uw tuin een straat, fietspad of voetpad ligt, beantwoordt u de vraag met ‘ja’.",
          "type": "boolean",
          "prio": 10120,
          "id": "b842a38d8942825f4a7f8c7fe8bc04e7"
        },
        {
          "text": "U gaat een kozijn plaatsen aan de achterkant van het gebouw. Ligt die kant aan een gracht, kanaal of ander vaarwater waar iedereen mag komen?",
          "description": "![Kozijnen in de achtergevel. De achtergevel ligt aan vaarwater.](https://sttr-files.flolegal.app/00000001002564440000/OTG_Achterkant-water_01.png \"Achterkant aan een gracht, kanaal of ander vaarwater.\")\n\nAls er direct achter uw tuin een gracht, kanaal of ander vaarwater ligt, beantwoordt u de vraag met ‘ja’.",
          "type": "boolean",
          "prio": 10130,
          "id": "e31a385ab7e5cfb2d2a0a0291831de24"
        },
        {
          "text": "U gaat een kozijn plaatsen aan de achterkant van het gebouw. Ligt die gevel aan een plein, park of parkeerplaats waar iedereen mag komen?",
          "description": "![Kozijnen in de achtergevel. De achtergevel ligt aan een plantsoen.](https://sttr-files.flolegal.app/00000001002564440000/OTG_Achterkant-plantsoen_01.png \"Achterkant aan een plein, park of parkeerplaats.\")\n\nAls er direct achter uw tuin een plein, park of parkeerplaats ligt, beantwoordt u de vraag met ‘ja’.",
          "type": "boolean",
          "prio": 10140,
          "id": "ba737150a80b67f3e58d264e2cdce407"
        }
      ],
      "decisions": {
        "c99c17a6bdbc88fb569b386c334e22d1": {
          "requiredInputs": [
            "1eadce5a190e452699c0b7620386c2ac",
            "25cb5125db81edc8c6404ce76e9b62c9"
          ],
          "decisionTable": {
            "rules": [
              {
                "inputs": [
                  "\"Rijksmonument\"",
                  "\"Ik ga een nieuw kozijn plaatsen op een plek waar er eerst geen was.\""
                ],
                "output": "\"Vergunningplicht\""
              },
              {
                "inputs": [
                  "\"Gemeentelijk monument\"",
                  "\"Ik ga een nieuw kozijn plaatsen op een plek waar er eerst geen was.\""
                ],
                "output": "\"Vergunningplicht\""
              },
              {
                "inputs": ["\"Geen monument\"", "-"],
                "output": "\"no hit\""
              },
              {
                "inputs": [
                  "-",
                  "\"Ik ga een kozijn plaatsen of vernieuwen op een plek waar er eerst al een was.\""
                ],
                "output": "\"no hit\""
              }
            ]
          }
        },
        "e76509c142b257650275507d47278569": {
          "requiredInputs": [
            "1eadce5a190e452699c0b7620386c2ac",
            "ab7ad575972c1cb19bffde2977c00c2b",
            "00e898edcd392d99fd044cc7556d1130"
          ],
          "decisionTable": {
            "rules": [
              {
                "inputs": [
                  "\"Geen monument\"",
                  "\"Ik ga een nieuw kozijn plaatsen op een plek waar er eerst geen was.\"",
                  "\"In een aanbouw, uitbouw of bijgebouw\""
                ],
                "output": "\"NeemContactOpMet\""
              },
              {
                "inputs": ["\"Rijksmonument\"", "-", "-"],
                "output": "\"no hit\""
              },
              {
                "inputs": ["\"Gemeentelijk monument\"", "-", "-"],
                "output": "\"no hit\""
              },
              {
                "inputs": [
                  "-",
                  "\"Ik ga een kozijn plaatsen of vernieuwen op een plek waar er eerst al een was.\"",
                  "-"
                ],
                "output": "\"no hit\""
              },
              {
                "inputs": ["-", "-", "\"In een hoofdgebouw\""],
                "output": "\"no hit\""
              }
            ]
          }
        },
        "c53d216cc5f7dfdc4081f284fbbd5d2a": {
          "requiredInputs": [
            "1eadce5a190e452699c0b7620386c2ac",
            "25cb5125db81edc8c6404ce76e9b62c9",
            "1f01e0c37fd56dc8800380fd77541dcf"
          ],
          "decisionTable": {
            "rules": [
              {
                "inputs": [
                  "\"Rijksmonument\"",
                  "\"Ik ga een kozijn plaatsen of vernieuwen op een plek waar er eerst al een was.\"",
                  "\"Ja, het kozijn verandert.\""
                ],
                "output": "\"Vergunningplicht\""
              },
              {
                "inputs": [
                  "\"Gemeentelijk monument\"",
                  "\"Ik ga een kozijn plaatsen of vernieuwen op een plek waar er eerst al een was.\"",
                  "\"Ja, het kozijn verandert.\""
                ],
                "output": "\"Vergunningplicht\""
              },
              {
                "inputs": ["\"Geen monument\"", "-", "-"],
                "output": "\"no hit\""
              },
              {
                "inputs": [
                  "-",
                  "\"Ik ga een nieuw kozijn plaatsen op een plek waar er eerst geen was.\"",
                  "-"
                ],
                "output": "\"no hit\""
              },
              {
                "inputs": [
                  "-",
                  "-",
                  "\"Nee, de vorm, de grootte en het profiel veranderen niet. Ook kleur en materiaal veranderen niet.\""
                ],
                "output": "\"no hit\""
              }
            ]
          }
        },
        "f9dabc794c6c8958fdf8c65ca31dbd27": {
          "requiredInputs": [
            "1eadce5a190e452699c0b7620386c2ac",
            "ab7ad575972c1cb19bffde2977c00c2b",
            "8b312e9536ed39e46c3c0ea6248cb709",
            "00e898edcd392d99fd044cc7556d1130"
          ],
          "decisionTable": {
            "rules": [
              {
                "inputs": [
                  "\"Geen monument\"",
                  "\"Ik ga een kozijn plaatsen of vernieuwen op een plek waar er eerst al een was.\"",
                  "\"Ja, de vorm, de grootte of het profiel verandert.\"",
                  "\"In een aanbouw, uitbouw of bijgebouw\""
                ],
                "output": "\"NeemContactOpMet\""
              },
              {
                "inputs": ["\"Rijksmonument\"", "-", "-", "-"],
                "output": "\"no hit\""
              },
              {
                "inputs": ["\"Gemeentelijk monument\"", "-", "-", "-"],
                "output": "\"no hit\""
              },
              {
                "inputs": [
                  "-",
                  "\"Ik ga een nieuw kozijn plaatsen op een plek waar er eerst geen was.\"",
                  "-",
                  "-"
                ],
                "output": "\"no hit\""
              },
              {
                "inputs": [
                  "-",
                  "-",
                  "\"Nee, de vorm, de grootte en het profiel veranderen niet.\"",
                  "-"
                ],
                "output": "\"no hit\""
              },
              {
                "inputs": ["-", "-", "-", "\"In een hoofdgebouw\""],
                "output": "\"no hit\""
              }
            ]
          }
        },
        "90604cba0b2648875090de04ac9bdead": {
          "requiredInputs": [
            "1eadce5a190e452699c0b7620386c2ac",
            "ab7ad575972c1cb19bffde2977c00c2b",
            "e3c7868ee0fd5e496855f3462fc029f7",
            "00e898edcd392d99fd044cc7556d1130",
            "d49ca838fb038c0ead04dbf81fef24c5"
          ],
          "decisionTable": {
            "rules": [
              {
                "inputs": [
                  "\"Geen monument\"",
                  "\"Ik ga een nieuw kozijn plaatsen op een plek waar er eerst geen was.\"",
                  "\"Ja, het gebouw ligt in een rijksbeschermd stads- of dorpsgezicht.\"",
                  "\"In een hoofdgebouw\"",
                  "\"Voorkant\""
                ],
                "output": "\"Vergunningplicht\""
              },
              {
                "inputs": [
                  "\"Geen monument\"",
                  "\"Ik ga een nieuw kozijn plaatsen op een plek waar er eerst geen was.\"",
                  "\"Ja, het gebouw ligt in een gemeentelijk beschermd stads- of dorpsgezicht.\"",
                  "\"In een hoofdgebouw\"",
                  "\"Voorkant\""
                ],
                "output": "\"Vergunningplicht\""
              },
              {
                "inputs": [
                  "\"Geen monument\"",
                  "\"Ik ga een nieuw kozijn plaatsen op een plek waar er eerst geen was.\"",
                  "\"Nee, het gebouw ligt niet in een beschermd stads- of dorpsgezicht.\"",
                  "\"In een hoofdgebouw\"",
                  "\"Voorkant\""
                ],
                "output": "\"Vergunningplicht\""
              },
              {
                "inputs": [
                  "\"Geen monument\"",
                  "\"Ik ga een nieuw kozijn plaatsen op een plek waar er eerst geen was.\"",
                  "\"Ja, het gebouw ligt in een rijksbeschermd stads- of dorpsgezicht.\"",
                  "\"In een hoofdgebouw\"",
                  "\"Zijkant\""
                ],
                "output": "\"Vergunningplicht\""
              },
              {
                "inputs": ["\"Rijksmonument\"", "-", "-", "-", "-"],
                "output": "\"no hit\""
              },
              {
                "inputs": ["\"Gemeentelijk monument\"", "-", "-", "-", "-"],
                "output": "\"no hit\""
              },
              {
                "inputs": [
                  "-",
                  "\"Ik ga een kozijn plaatsen of vernieuwen op een plek waar er eerst al een was.\"",
                  "-",
                  "-",
                  "-"
                ],
                "output": "\"no hit\""
              },
              {
                "inputs": [
                  "-",
                  "-",
                  "-",
                  "\"In een aanbouw, uitbouw of bijgebouw\"",
                  "-"
                ],
                "output": "\"no hit\""
              },
              {
                "inputs": ["-", "-", "-", "-", "\"Achterkant\""],
                "output": "\"no hit\""
              }
            ]
          }
        },
        "4f33a93ea5bd5cc7c0efe5677e5d769f": {
          "requiredInputs": [
            "1eadce5a190e452699c0b7620386c2ac",
            "ab7ad575972c1cb19bffde2977c00c2b",
            "e3c7868ee0fd5e496855f3462fc029f7",
            "00e898edcd392d99fd044cc7556d1130",
            "d49ca838fb038c0ead04dbf81fef24c5",
            "c13ff0b1421c4e4c179244d584ae4c1f"
          ],
          "decisionTable": {
            "rules": [
              {
                "inputs": [
                  "\"Geen monument\"",
                  "\"Ik ga een nieuw kozijn plaatsen op een plek waar er eerst geen was.\"",
                  "\"Ja, het gebouw ligt in een gemeentelijk beschermd stads- of dorpsgezicht.\"",
                  "\"In een hoofdgebouw\"",
                  "\"Zijkant\"",
                  true
                ],
                "output": "\"Vergunningplicht\""
              },
              {
                "inputs": [
                  "\"Geen monument\"",
                  "\"Ik ga een nieuw kozijn plaatsen op een plek waar er eerst geen was.\"",
                  "\"Nee, het gebouw ligt niet in een beschermd stads- of dorpsgezicht.\"",
                  "\"In een hoofdgebouw\"",
                  "\"Zijkant\"",
                  true
                ],
                "output": "\"Vergunningplicht\""
              },
              {
                "inputs": ["\"Rijksmonument\"", "-", "-", "-", "-", "-"],
                "output": "\"no hit\""
              },
              {
                "inputs": [
                  "\"Gemeentelijk monument\"",
                  "-",
                  "-",
                  "-",
                  "-",
                  "-"
                ],
                "output": "\"no hit\""
              },
              {
                "inputs": [
                  "-",
                  "\"Ik ga een kozijn plaatsen of vernieuwen op een plek waar er eerst al een was.\"",
                  "-",
                  "-",
                  "-",
                  "-"
                ],
                "output": "\"no hit\""
              },
              {
                "inputs": [
                  "-",
                  "-",
                  "\"Ja, het gebouw ligt in een rijksbeschermd stads- of dorpsgezicht.\"",
                  "-",
                  "-",
                  "-"
                ],
                "output": "\"no hit\""
              },
              {
                "inputs": [
                  "-",
                  "-",
                  "-",
                  "\"In een aanbouw, uitbouw of bijgebouw\"",
                  "-",
                  "-"
                ],
                "output": "\"no hit\""
              },
              {
                "inputs": ["-", "-", "-", "-", "\"Voorkant\"", "-"],
                "output": "\"no hit\""
              },
              {
                "inputs": ["-", "-", "-", "-", "\"Achterkant\"", "-"],
                "output": "\"no hit\""
              },
              {
                "inputs": ["-", "-", "-", "-", "-", false],
                "output": "\"no hit\""
              }
            ]
          }
        },
        "724f7957962a90c0e6293a631c5bca56": {
          "requiredInputs": [
            "1eadce5a190e452699c0b7620386c2ac",
            "ab7ad575972c1cb19bffde2977c00c2b",
            "8b312e9536ed39e46c3c0ea6248cb709",
            "e3c7868ee0fd5e496855f3462fc029f7",
            "00e898edcd392d99fd044cc7556d1130",
            "d49ca838fb038c0ead04dbf81fef24c5"
          ],
          "decisionTable": {
            "rules": [
              {
                "inputs": [
                  "\"Geen monument\"",
                  "\"Ik ga een kozijn plaatsen of vernieuwen op een plek waar er eerst al een was.\"",
                  "\"Ja, de vorm, de grootte of het profiel verandert.\"",
                  "\"Ja, het gebouw ligt in een rijksbeschermd stads- of dorpsgezicht.\"",
                  "\"In een hoofdgebouw\"",
                  "\"Voorkant\""
                ],
                "output": "\"Vergunningplicht\""
              },
              {
                "inputs": [
                  "\"Geen monument\"",
                  "\"Ik ga een kozijn plaatsen of vernieuwen op een plek waar er eerst al een was.\"",
                  "\"Ja, de vorm, de grootte of het profiel verandert.\"",
                  "\"Ja, het gebouw ligt in een gemeentelijk beschermd stads- of dorpsgezicht.\"",
                  "\"In een hoofdgebouw\"",
                  "\"Voorkant\""
                ],
                "output": "\"Vergunningplicht\""
              },
              {
                "inputs": [
                  "\"Geen monument\"",
                  "\"Ik ga een kozijn plaatsen of vernieuwen op een plek waar er eerst al een was.\"",
                  "\"Ja, de vorm, de grootte of het profiel verandert.\"",
                  "\"Nee, het gebouw ligt niet in een beschermd stads- of dorpsgezicht.\"",
                  "\"In een hoofdgebouw\"",
                  "\"Voorkant\""
                ],
                "output": "\"Vergunningplicht\""
              },
              {
                "inputs": [
                  "\"Geen monument\"",
                  "\"Ik ga een kozijn plaatsen of vernieuwen op een plek waar er eerst al een was.\"",
                  "\"Ja, de vorm, de grootte of het profiel verandert.\"",
                  "\"Ja, het gebouw ligt in een rijksbeschermd stads- of dorpsgezicht.\"",
                  "\"In een hoofdgebouw\"",
                  "\"Zijkant\""
                ],
                "output": "\"Vergunningplicht\""
              },
              {
                "inputs": ["\"Rijksmonument\"", "-", "-", "-", "-", "-"],
                "output": "\"no hit\""
              },
              {
                "inputs": [
                  "\"Gemeentelijk monument\"",
                  "-",
                  "-",
                  "-",
                  "-",
                  "-"
                ],
                "output": "\"no hit\""
              },
              {
                "inputs": [
                  "-",
                  "\"Ik ga een nieuw kozijn plaatsen op een plek waar er eerst geen was.\"",
                  "-",
                  "-",
                  "-",
                  "-"
                ],
                "output": "\"no hit\""
              },
              {
                "inputs": [
                  "-",
                  "-",
                  "\"Nee, de vorm, de grootte en het profiel veranderen niet.\"",
                  "-",
                  "-",
                  "-"
                ],
                "output": "\"no hit\""
              },
              {
                "inputs": [
                  "-",
                  "-",
                  "-",
                  "-",
                  "\"In een aanbouw, uitbouw of bijgebouw\"",
                  "-"
                ],
                "output": "\"no hit\""
              },
              {
                "inputs": ["-", "-", "-", "-", "-", "\"Achterkant\""],
                "output": "\"no hit\""
              }
            ]
          }
        },
        "2f8f7f86c790b26baab89a36ee0f27b3": {
          "requiredInputs": [
            "1eadce5a190e452699c0b7620386c2ac",
            "ab7ad575972c1cb19bffde2977c00c2b",
            "e3c7868ee0fd5e496855f3462fc029f7",
            "00e898edcd392d99fd044cc7556d1130",
            "d49ca838fb038c0ead04dbf81fef24c5",
            "b842a38d8942825f4a7f8c7fe8bc04e7"
          ],
          "decisionTable": {
            "rules": [
              {
                "inputs": [
                  "\"Geen monument\"",
                  "\"Ik ga een nieuw kozijn plaatsen op een plek waar er eerst geen was.\"",
                  "\"Ja, het gebouw ligt in een rijksbeschermd stads- of dorpsgezicht.\"",
                  "\"In een hoofdgebouw\"",
                  "\"Achterkant\"",
                  true
                ],
                "output": "\"Vergunningplicht\""
              },
              {
                "inputs": ["\"Rijksmonument\"", "-", "-", "-", "-", "-"],
                "output": "\"no hit\""
              },
              {
                "inputs": [
                  "\"Gemeentelijk monument\"",
                  "-",
                  "-",
                  "-",
                  "-",
                  "-"
                ],
                "output": "\"no hit\""
              },
              {
                "inputs": [
                  "-",
                  "\"Ik ga een kozijn plaatsen of vernieuwen op een plek waar er eerst al een was.\"",
                  "-",
                  "-",
                  "-",
                  "-"
                ],
                "output": "\"no hit\""
              },
              {
                "inputs": [
                  "-",
                  "-",
                  "\"Ja, het gebouw ligt in een gemeentelijk beschermd stads- of dorpsgezicht.\"",
                  "-",
                  "-",
                  "-"
                ],
                "output": "\"no hit\""
              },
              {
                "inputs": [
                  "-",
                  "-",
                  "\"Nee, het gebouw ligt niet in een beschermd stads- of dorpsgezicht.\"",
                  "-",
                  "-",
                  "-"
                ],
                "output": "\"no hit\""
              },
              {
                "inputs": [
                  "-",
                  "-",
                  "-",
                  "\"In een aanbouw, uitbouw of bijgebouw\"",
                  "-",
                  "-"
                ],
                "output": "\"no hit\""
              },
              {
                "inputs": ["-", "-", "-", "-", "\"Voorkant\"", "-"],
                "output": "\"no hit\""
              },
              {
                "inputs": ["-", "-", "-", "-", "\"Zijkant\"", "-"],
                "output": "\"no hit\""
              },
              {
                "inputs": ["-", "-", "-", "-", "-", false],
                "output": "\"no hit\""
              }
            ]
          }
        },
        "56a34f164e07f0a92732c4d2e2a09908": {
          "requiredInputs": [
            "1eadce5a190e452699c0b7620386c2ac",
            "ab7ad575972c1cb19bffde2977c00c2b",
            "e3c7868ee0fd5e496855f3462fc029f7",
            "00e898edcd392d99fd044cc7556d1130",
            "d49ca838fb038c0ead04dbf81fef24c5",
            "b842a38d8942825f4a7f8c7fe8bc04e7",
            "e31a385ab7e5cfb2d2a0a0291831de24"
          ],
          "decisionTable": {
            "rules": [
              {
                "inputs": [
                  "\"Geen monument\"",
                  "\"Ik ga een nieuw kozijn plaatsen op een plek waar er eerst geen was.\"",
                  "\"Ja, het gebouw ligt in een rijksbeschermd stads- of dorpsgezicht.\"",
                  "\"In een hoofdgebouw\"",
                  "\"Achterkant\"",
                  false,
                  true
                ],
                "output": "\"Vergunningplicht\""
              },
              {
                "inputs": ["\"Rijksmonument\"", "-", "-", "-", "-", "-", "-"],
                "output": "\"no hit\""
              },
              {
                "inputs": [
                  "\"Gemeentelijk monument\"",
                  "-",
                  "-",
                  "-",
                  "-",
                  "-",
                  "-"
                ],
                "output": "\"no hit\""
              },
              {
                "inputs": [
                  "-",
                  "\"Ik ga een kozijn plaatsen of vernieuwen op een plek waar er eerst al een was.\"",
                  "-",
                  "-",
                  "-",
                  "-",
                  "-"
                ],
                "output": "\"no hit\""
              },
              {
                "inputs": [
                  "-",
                  "-",
                  "\"Ja, het gebouw ligt in een gemeentelijk beschermd stads- of dorpsgezicht.\"",
                  "-",
                  "-",
                  "-",
                  "-"
                ],
                "output": "\"no hit\""
              },
              {
                "inputs": [
                  "-",
                  "-",
                  "\"Nee, het gebouw ligt niet in een beschermd stads- of dorpsgezicht.\"",
                  "-",
                  "-",
                  "-",
                  "-"
                ],
                "output": "\"no hit\""
              },
              {
                "inputs": [
                  "-",
                  "-",
                  "-",
                  "\"In een aanbouw, uitbouw of bijgebouw\"",
                  "-",
                  "-",
                  "-"
                ],
                "output": "\"no hit\""
              },
              {
                "inputs": ["-", "-", "-", "-", "\"Voorkant\"", "-", "-"],
                "output": "\"no hit\""
              },
              {
                "inputs": ["-", "-", "-", "-", "\"Zijkant\"", "-", "-"],
                "output": "\"no hit\""
              },
              {
                "inputs": ["-", "-", "-", "-", "-", true, "-"],
                "output": "\"no hit\""
              },
              {
                "inputs": ["-", "-", "-", "-", "-", "-", false],
                "output": "\"no hit\""
              }
            ]
          }
        },
        "27ab07c61477af40760e3fbb423bd0bc": {
          "requiredInputs": [
            "1eadce5a190e452699c0b7620386c2ac",
            "ab7ad575972c1cb19bffde2977c00c2b",
            "e3c7868ee0fd5e496855f3462fc029f7",
            "00e898edcd392d99fd044cc7556d1130",
            "d49ca838fb038c0ead04dbf81fef24c5",
            "c13ff0b1421c4e4c179244d584ae4c1f",
            "34fc5a5b84202066fa3e29c6946939c1"
          ],
          "decisionTable": {
            "rules": [
              {
                "inputs": [
                  "\"Geen monument\"",
                  "\"Ik ga een nieuw kozijn plaatsen op een plek waar er eerst geen was.\"",
                  "\"Ja, het gebouw ligt in een gemeentelijk beschermd stads- of dorpsgezicht.\"",
                  "\"In een hoofdgebouw\"",
                  "\"Zijkant\"",
                  false,
                  true
                ],
                "output": "\"Vergunningplicht\""
              },
              {
                "inputs": [
                  "\"Geen monument\"",
                  "\"Ik ga een nieuw kozijn plaatsen op een plek waar er eerst geen was.\"",
                  "\"Nee, het gebouw ligt niet in een beschermd stads- of dorpsgezicht.\"",
                  "\"In een hoofdgebouw\"",
                  "\"Zijkant\"",
                  false,
                  true
                ],
                "output": "\"Vergunningplicht\""
              },
              {
                "inputs": ["\"Rijksmonument\"", "-", "-", "-", "-", "-", "-"],
                "output": "\"no hit\""
              },
              {
                "inputs": [
                  "\"Gemeentelijk monument\"",
                  "-",
                  "-",
                  "-",
                  "-",
                  "-",
                  "-"
                ],
                "output": "\"no hit\""
              },
              {
                "inputs": [
                  "-",
                  "\"Ik ga een kozijn plaatsen of vernieuwen op een plek waar er eerst al een was.\"",
                  "-",
                  "-",
                  "-",
                  "-",
                  "-"
                ],
                "output": "\"no hit\""
              },
              {
                "inputs": [
                  "-",
                  "-",
                  "\"Ja, het gebouw ligt in een rijksbeschermd stads- of dorpsgezicht.\"",
                  "-",
                  "-",
                  "-",
                  "-"
                ],
                "output": "\"no hit\""
              },
              {
                "inputs": [
                  "-",
                  "-",
                  "-",
                  "\"In een aanbouw, uitbouw of bijgebouw\"",
                  "-",
                  "-",
                  "-"
                ],
                "output": "\"no hit\""
              },
              {
                "inputs": ["-", "-", "-", "-", "\"Voorkant\"", "-", "-"],
                "output": "\"no hit\""
              },
              {
                "inputs": ["-", "-", "-", "-", "\"Achterkant\"", "-", "-"],
                "output": "\"no hit\""
              },
              {
                "inputs": ["-", "-", "-", "-", "-", true, "-"],
                "output": "\"no hit\""
              },
              {
                "inputs": ["-", "-", "-", "-", "-", "-", false],
                "output": "\"no hit\""
              }
            ]
          }
        },
        "b33dbd97ca479280ce028aa10b71214a": {
          "requiredInputs": [
            "1eadce5a190e452699c0b7620386c2ac",
            "ab7ad575972c1cb19bffde2977c00c2b",
            "8b312e9536ed39e46c3c0ea6248cb709",
            "e3c7868ee0fd5e496855f3462fc029f7",
            "00e898edcd392d99fd044cc7556d1130",
            "d49ca838fb038c0ead04dbf81fef24c5",
            "b842a38d8942825f4a7f8c7fe8bc04e7"
          ],
          "decisionTable": {
            "rules": [
              {
                "inputs": [
                  "\"Geen monument\"",
                  "\"Ik ga een kozijn plaatsen of vernieuwen op een plek waar er eerst al een was.\"",
                  "\"Ja, de vorm, de grootte of het profiel verandert.\"",
                  "\"Ja, het gebouw ligt in een rijksbeschermd stads- of dorpsgezicht.\"",
                  "\"In een hoofdgebouw\"",
                  "\"Achterkant\"",
                  true
                ],
                "output": "\"Vergunningplicht\""
              },
              {
                "inputs": ["\"Rijksmonument\"", "-", "-", "-", "-", "-", "-"],
                "output": "\"no hit\""
              },
              {
                "inputs": [
                  "\"Gemeentelijk monument\"",
                  "-",
                  "-",
                  "-",
                  "-",
                  "-",
                  "-"
                ],
                "output": "\"no hit\""
              },
              {
                "inputs": [
                  "-",
                  "\"Ik ga een nieuw kozijn plaatsen op een plek waar er eerst geen was.\"",
                  "-",
                  "-",
                  "-",
                  "-",
                  "-"
                ],
                "output": "\"no hit\""
              },
              {
                "inputs": [
                  "-",
                  "-",
                  "\"Nee, de vorm, de grootte en het profiel veranderen niet.\"",
                  "-",
                  "-",
                  "-",
                  "-"
                ],
                "output": "\"no hit\""
              },
              {
                "inputs": [
                  "-",
                  "-",
                  "-",
                  "\"Ja, het gebouw ligt in een gemeentelijk beschermd stads- of dorpsgezicht.\"",
                  "-",
                  "-",
                  "-"
                ],
                "output": "\"no hit\""
              },
              {
                "inputs": [
                  "-",
                  "-",
                  "-",
                  "\"Nee, het gebouw ligt niet in een beschermd stads- of dorpsgezicht.\"",
                  "-",
                  "-",
                  "-"
                ],
                "output": "\"no hit\""
              },
              {
                "inputs": [
                  "-",
                  "-",
                  "-",
                  "-",
                  "\"In een aanbouw, uitbouw of bijgebouw\"",
                  "-",
                  "-"
                ],
                "output": "\"no hit\""
              },
              {
                "inputs": ["-", "-", "-", "-", "-", "\"Voorkant\"", "-"],
                "output": "\"no hit\""
              },
              {
                "inputs": ["-", "-", "-", "-", "-", "\"Zijkant\"", "-"],
                "output": "\"no hit\""
              },
              {
                "inputs": ["-", "-", "-", "-", "-", "-", false],
                "output": "\"no hit\""
              }
            ]
          }
        },
        "6fd9039462721cdbd8125a12b4f9b2f4": {
          "requiredInputs": [
            "1eadce5a190e452699c0b7620386c2ac",
            "ab7ad575972c1cb19bffde2977c00c2b",
            "8b312e9536ed39e46c3c0ea6248cb709",
            "e3c7868ee0fd5e496855f3462fc029f7",
            "00e898edcd392d99fd044cc7556d1130",
            "d49ca838fb038c0ead04dbf81fef24c5",
            "c13ff0b1421c4e4c179244d584ae4c1f"
          ],
          "decisionTable": {
            "rules": [
              {
                "inputs": [
                  "\"Geen monument\"",
                  "\"Ik ga een kozijn plaatsen of vernieuwen op een plek waar er eerst al een was.\"",
                  "\"Ja, de vorm, de grootte of het profiel verandert.\"",
                  "\"Ja, het gebouw ligt in een gemeentelijk beschermd stads- of dorpsgezicht.\"",
                  "\"In een hoofdgebouw\"",
                  "\"Zijkant\"",
                  true
                ],
                "output": "\"Vergunningplicht\""
              },
              {
                "inputs": [
                  "\"Geen monument\"",
                  "\"Ik ga een kozijn plaatsen of vernieuwen op een plek waar er eerst al een was.\"",
                  "\"Ja, de vorm, de grootte of het profiel verandert.\"",
                  "\"Nee, het gebouw ligt niet in een beschermd stads- of dorpsgezicht.\"",
                  "\"In een hoofdgebouw\"",
                  "\"Zijkant\"",
                  true
                ],
                "output": "\"Vergunningplicht\""
              },
              {
                "inputs": ["\"Rijksmonument\"", "-", "-", "-", "-", "-", "-"],
                "output": "\"no hit\""
              },
              {
                "inputs": [
                  "\"Gemeentelijk monument\"",
                  "-",
                  "-",
                  "-",
                  "-",
                  "-",
                  "-"
                ],
                "output": "\"no hit\""
              },
              {
                "inputs": [
                  "-",
                  "\"Ik ga een nieuw kozijn plaatsen op een plek waar er eerst geen was.\"",
                  "-",
                  "-",
                  "-",
                  "-",
                  "-"
                ],
                "output": "\"no hit\""
              },
              {
                "inputs": [
                  "-",
                  "-",
                  "\"Nee, de vorm, de grootte en het profiel veranderen niet.\"",
                  "-",
                  "-",
                  "-",
                  "-"
                ],
                "output": "\"no hit\""
              },
              {
                "inputs": [
                  "-",
                  "-",
                  "-",
                  "\"Ja, het gebouw ligt in een rijksbeschermd stads- of dorpsgezicht.\"",
                  "-",
                  "-",
                  "-"
                ],
                "output": "\"no hit\""
              },
              {
                "inputs": [
                  "-",
                  "-",
                  "-",
                  "-",
                  "\"In een aanbouw, uitbouw of bijgebouw\"",
                  "-",
                  "-"
                ],
                "output": "\"no hit\""
              },
              {
                "inputs": ["-", "-", "-", "-", "-", "\"Voorkant\"", "-"],
                "output": "\"no hit\""
              },
              {
                "inputs": ["-", "-", "-", "-", "-", "\"Achterkant\"", "-"],
                "output": "\"no hit\""
              },
              {
                "inputs": ["-", "-", "-", "-", "-", "-", false],
                "output": "\"no hit\""
              }
            ]
          }
        },
        "557285192983e6c96e9aee8160823835": {
          "requiredInputs": [
            "1eadce5a190e452699c0b7620386c2ac",
            "ab7ad575972c1cb19bffde2977c00c2b",
            "e3c7868ee0fd5e496855f3462fc029f7",
            "00e898edcd392d99fd044cc7556d1130",
            "d49ca838fb038c0ead04dbf81fef24c5",
            "c13ff0b1421c4e4c179244d584ae4c1f",
            "34fc5a5b84202066fa3e29c6946939c1",
            "3fe613f807f0a5ee93b535b6ac05f880"
          ],
          "decisionTable": {
            "rules": [
              {
                "inputs": [
                  "\"Geen monument\"",
                  "\"Ik ga een nieuw kozijn plaatsen op een plek waar er eerst geen was.\"",
                  "\"Ja, het gebouw ligt in een gemeentelijk beschermd stads- of dorpsgezicht.\"",
                  "\"In een hoofdgebouw\"",
                  "\"Zijkant\"",
                  false,
                  false,
                  true
                ],
                "output": "\"Vergunningplicht\""
              },
              {
                "inputs": [
                  "\"Geen monument\"",
                  "\"Ik ga een nieuw kozijn plaatsen op een plek waar er eerst geen was.\"",
                  "\"Nee, het gebouw ligt niet in een beschermd stads- of dorpsgezicht.\"",
                  "\"In een hoofdgebouw\"",
                  "\"Zijkant\"",
                  false,
                  false,
                  true
                ],
                "output": "\"Vergunningplicht\""
              },
              {
                "inputs": [
                  "\"Rijksmonument\"",
                  "-",
                  "-",
                  "-",
                  "-",
                  "-",
                  "-",
                  "-"
                ],
                "output": "\"no hit\""
              },
              {
                "inputs": [
                  "\"Gemeentelijk monument\"",
                  "-",
                  "-",
                  "-",
                  "-",
                  "-",
                  "-",
                  "-"
                ],
                "output": "\"no hit\""
              },
              {
                "inputs": [
                  "-",
                  "\"Ik ga een kozijn plaatsen of vernieuwen op een plek waar er eerst al een was.\"",
                  "-",
                  "-",
                  "-",
                  "-",
                  "-",
                  "-"
                ],
                "output": "\"no hit\""
              },
              {
                "inputs": [
                  "-",
                  "-",
                  "\"Ja, het gebouw ligt in een rijksbeschermd stads- of dorpsgezicht.\"",
                  "-",
                  "-",
                  "-",
                  "-",
                  "-"
                ],
                "output": "\"no hit\""
              },
              {
                "inputs": [
                  "-",
                  "-",
                  "-",
                  "\"In een aanbouw, uitbouw of bijgebouw\"",
                  "-",
                  "-",
                  "-",
                  "-"
                ],
                "output": "\"no hit\""
              },
              {
                "inputs": ["-", "-", "-", "-", "\"Voorkant\"", "-", "-", "-"],
                "output": "\"no hit\""
              },
              {
                "inputs": ["-", "-", "-", "-", "\"Achterkant\"", "-", "-", "-"],
                "output": "\"no hit\""
              },
              {
                "inputs": ["-", "-", "-", "-", "-", true, "-", "-"],
                "output": "\"no hit\""
              },
              {
                "inputs": ["-", "-", "-", "-", "-", "-", true, "-"],
                "output": "\"no hit\""
              },
              {
                "inputs": ["-", "-", "-", "-", "-", "-", "-", false],
                "output": "\"no hit\""
              }
            ]
          }
        },
        "8bdbd484130d64d341727787050f0373": {
          "requiredInputs": [
            "1eadce5a190e452699c0b7620386c2ac",
            "ab7ad575972c1cb19bffde2977c00c2b",
            "8b312e9536ed39e46c3c0ea6248cb709",
            "e3c7868ee0fd5e496855f3462fc029f7",
            "00e898edcd392d99fd044cc7556d1130",
            "d49ca838fb038c0ead04dbf81fef24c5",
            "b842a38d8942825f4a7f8c7fe8bc04e7",
            "e31a385ab7e5cfb2d2a0a0291831de24"
          ],
          "decisionTable": {
            "rules": [
              {
                "inputs": [
                  "\"Geen monument\"",
                  "\"Ik ga een kozijn plaatsen of vernieuwen op een plek waar er eerst al een was.\"",
                  "\"Ja, de vorm, de grootte of het profiel verandert.\"",
                  "\"Ja, het gebouw ligt in een rijksbeschermd stads- of dorpsgezicht.\"",
                  "\"In een hoofdgebouw\"",
                  "\"Achterkant\"",
                  false,
                  true
                ],
                "output": "\"Vergunningplicht\""
              },
              {
                "inputs": [
                  "\"Rijksmonument\"",
                  "-",
                  "-",
                  "-",
                  "-",
                  "-",
                  "-",
                  "-"
                ],
                "output": "\"no hit\""
              },
              {
                "inputs": [
                  "\"Gemeentelijk monument\"",
                  "-",
                  "-",
                  "-",
                  "-",
                  "-",
                  "-",
                  "-"
                ],
                "output": "\"no hit\""
              },
              {
                "inputs": [
                  "-",
                  "\"Ik ga een nieuw kozijn plaatsen op een plek waar er eerst geen was.\"",
                  "-",
                  "-",
                  "-",
                  "-",
                  "-",
                  "-"
                ],
                "output": "\"no hit\""
              },
              {
                "inputs": [
                  "-",
                  "-",
                  "\"Nee, de vorm, de grootte en het profiel veranderen niet.\"",
                  "-",
                  "-",
                  "-",
                  "-",
                  "-"
                ],
                "output": "\"no hit\""
              },
              {
                "inputs": [
                  "-",
                  "-",
                  "-",
                  "\"Ja, het gebouw ligt in een gemeentelijk beschermd stads- of dorpsgezicht.\"",
                  "-",
                  "-",
                  "-",
                  "-"
                ],
                "output": "\"no hit\""
              },
              {
                "inputs": [
                  "-",
                  "-",
                  "-",
                  "\"Nee, het gebouw ligt niet in een beschermd stads- of dorpsgezicht.\"",
                  "-",
                  "-",
                  "-",
                  "-"
                ],
                "output": "\"no hit\""
              },
              {
                "inputs": [
                  "-",
                  "-",
                  "-",
                  "-",
                  "\"In een aanbouw, uitbouw of bijgebouw\"",
                  "-",
                  "-",
                  "-"
                ],
                "output": "\"no hit\""
              },
              {
                "inputs": ["-", "-", "-", "-", "-", "\"Voorkant\"", "-", "-"],
                "output": "\"no hit\""
              },
              {
                "inputs": ["-", "-", "-", "-", "-", "\"Zijkant\"", "-", "-"],
                "output": "\"no hit\""
              },
              {
                "inputs": ["-", "-", "-", "-", "-", "-", true, "-"],
                "output": "\"no hit\""
              },
              {
                "inputs": ["-", "-", "-", "-", "-", "-", "-", false],
                "output": "\"no hit\""
              }
            ]
          }
        },
        "05798c198bb3a36ecd06f1dba165e5da": {
          "requiredInputs": [
            "1eadce5a190e452699c0b7620386c2ac",
            "ab7ad575972c1cb19bffde2977c00c2b",
            "e3c7868ee0fd5e496855f3462fc029f7",
            "00e898edcd392d99fd044cc7556d1130",
            "d49ca838fb038c0ead04dbf81fef24c5",
            "b842a38d8942825f4a7f8c7fe8bc04e7",
            "e31a385ab7e5cfb2d2a0a0291831de24",
            "ba737150a80b67f3e58d264e2cdce407"
          ],
          "decisionTable": {
            "rules": [
              {
                "inputs": [
                  "\"Geen monument\"",
                  "\"Ik ga een nieuw kozijn plaatsen op een plek waar er eerst geen was.\"",
                  "\"Ja, het gebouw ligt in een rijksbeschermd stads- of dorpsgezicht.\"",
                  "\"In een hoofdgebouw\"",
                  "\"Achterkant\"",
                  false,
                  false,
                  true
                ],
                "output": "\"Vergunningplicht\""
              },
              {
                "inputs": [
                  "\"Rijksmonument\"",
                  "-",
                  "-",
                  "-",
                  "-",
                  "-",
                  "-",
                  "-"
                ],
                "output": "\"no hit\""
              },
              {
                "inputs": [
                  "\"Gemeentelijk monument\"",
                  "-",
                  "-",
                  "-",
                  "-",
                  "-",
                  "-",
                  "-"
                ],
                "output": "\"no hit\""
              },
              {
                "inputs": [
                  "-",
                  "\"Ik ga een kozijn plaatsen of vernieuwen op een plek waar er eerst al een was.\"",
                  "-",
                  "-",
                  "-",
                  "-",
                  "-",
                  "-"
                ],
                "output": "\"no hit\""
              },
              {
                "inputs": [
                  "-",
                  "-",
                  "\"Ja, het gebouw ligt in een gemeentelijk beschermd stads- of dorpsgezicht.\"",
                  "-",
                  "-",
                  "-",
                  "-",
                  "-"
                ],
                "output": "\"no hit\""
              },
              {
                "inputs": [
                  "-",
                  "-",
                  "\"Nee, het gebouw ligt niet in een beschermd stads- of dorpsgezicht.\"",
                  "-",
                  "-",
                  "-",
                  "-",
                  "-"
                ],
                "output": "\"no hit\""
              },
              {
                "inputs": [
                  "-",
                  "-",
                  "-",
                  "\"In een aanbouw, uitbouw of bijgebouw\"",
                  "-",
                  "-",
                  "-",
                  "-"
                ],
                "output": "\"no hit\""
              },
              {
                "inputs": ["-", "-", "-", "-", "\"Voorkant\"", "-", "-", "-"],
                "output": "\"no hit\""
              },
              {
                "inputs": ["-", "-", "-", "-", "\"Zijkant\"", "-", "-", "-"],
                "output": "\"no hit\""
              },
              {
                "inputs": ["-", "-", "-", "-", "-", true, "-", "-"],
                "output": "\"no hit\""
              },
              {
                "inputs": ["-", "-", "-", "-", "-", "-", true, "-"],
                "output": "\"no hit\""
              },
              {
                "inputs": ["-", "-", "-", "-", "-", "-", "-", false],
                "output": "\"no hit\""
              }
            ]
          }
        },
        "81faae5f15e7912f51af1b8af730b4fc": {
          "requiredInputs": [
            "1eadce5a190e452699c0b7620386c2ac",
            "ab7ad575972c1cb19bffde2977c00c2b",
            "8b312e9536ed39e46c3c0ea6248cb709",
            "e3c7868ee0fd5e496855f3462fc029f7",
            "00e898edcd392d99fd044cc7556d1130",
            "d49ca838fb038c0ead04dbf81fef24c5",
            "c13ff0b1421c4e4c179244d584ae4c1f",
            "34fc5a5b84202066fa3e29c6946939c1"
          ],
          "decisionTable": {
            "rules": [
              {
                "inputs": [
                  "\"Geen monument\"",
                  "\"Ik ga een kozijn plaatsen of vernieuwen op een plek waar er eerst al een was.\"",
                  "\"Ja, de vorm, de grootte of het profiel verandert.\"",
                  "\"Ja, het gebouw ligt in een gemeentelijk beschermd stads- of dorpsgezicht.\"",
                  "\"In een hoofdgebouw\"",
                  "\"Zijkant\"",
                  false,
                  true
                ],
                "output": "\"Vergunningplicht\""
              },
              {
                "inputs": [
                  "\"Geen monument\"",
                  "\"Ik ga een kozijn plaatsen of vernieuwen op een plek waar er eerst al een was.\"",
                  "\"Ja, de vorm, de grootte of het profiel verandert.\"",
                  "\"Nee, het gebouw ligt niet in een beschermd stads- of dorpsgezicht.\"",
                  "\"In een hoofdgebouw\"",
                  "\"Zijkant\"",
                  false,
                  true
                ],
                "output": "\"Vergunningplicht\""
              },
              {
                "inputs": [
                  "\"Rijksmonument\"",
                  "-",
                  "-",
                  "-",
                  "-",
                  "-",
                  "-",
                  "-"
                ],
                "output": "\"no hit\""
              },
              {
                "inputs": [
                  "\"Gemeentelijk monument\"",
                  "-",
                  "-",
                  "-",
                  "-",
                  "-",
                  "-",
                  "-"
                ],
                "output": "\"no hit\""
              },
              {
                "inputs": [
                  "-",
                  "\"Ik ga een nieuw kozijn plaatsen op een plek waar er eerst geen was.\"",
                  "-",
                  "-",
                  "-",
                  "-",
                  "-",
                  "-"
                ],
                "output": "\"no hit\""
              },
              {
                "inputs": [
                  "-",
                  "-",
                  "\"Nee, de vorm, de grootte en het profiel veranderen niet.\"",
                  "-",
                  "-",
                  "-",
                  "-",
                  "-"
                ],
                "output": "\"no hit\""
              },
              {
                "inputs": [
                  "-",
                  "-",
                  "-",
                  "\"Ja, het gebouw ligt in een rijksbeschermd stads- of dorpsgezicht.\"",
                  "-",
                  "-",
                  "-",
                  "-"
                ],
                "output": "\"no hit\""
              },
              {
                "inputs": [
                  "-",
                  "-",
                  "-",
                  "-",
                  "\"In een aanbouw, uitbouw of bijgebouw\"",
                  "-",
                  "-",
                  "-"
                ],
                "output": "\"no hit\""
              },
              {
                "inputs": ["-", "-", "-", "-", "-", "\"Voorkant\"", "-", "-"],
                "output": "\"no hit\""
              },
              {
                "inputs": ["-", "-", "-", "-", "-", "\"Achterkant\"", "-", "-"],
                "output": "\"no hit\""
              },
              {
                "inputs": ["-", "-", "-", "-", "-", "-", true, "-"],
                "output": "\"no hit\""
              },
              {
                "inputs": ["-", "-", "-", "-", "-", "-", "-", false],
                "output": "\"no hit\""
              }
            ]
          }
        },
        "5fbf20134def73bb88295b2a4678b52c": {
          "requiredInputs": [
            "1eadce5a190e452699c0b7620386c2ac",
            "ab7ad575972c1cb19bffde2977c00c2b",
            "8b312e9536ed39e46c3c0ea6248cb709",
            "e3c7868ee0fd5e496855f3462fc029f7",
            "00e898edcd392d99fd044cc7556d1130",
            "d49ca838fb038c0ead04dbf81fef24c5",
            "b842a38d8942825f4a7f8c7fe8bc04e7",
            "e31a385ab7e5cfb2d2a0a0291831de24",
            "ba737150a80b67f3e58d264e2cdce407"
          ],
          "decisionTable": {
            "rules": [
              {
                "inputs": [
                  "\"Geen monument\"",
                  "\"Ik ga een kozijn plaatsen of vernieuwen op een plek waar er eerst al een was.\"",
                  "\"Ja, de vorm, de grootte of het profiel verandert.\"",
                  "\"Ja, het gebouw ligt in een rijksbeschermd stads- of dorpsgezicht.\"",
                  "\"In een hoofdgebouw\"",
                  "\"Achterkant\"",
                  false,
                  false,
                  true
                ],
                "output": "\"Vergunningplicht\""
              },
              {
                "inputs": [
                  "\"Rijksmonument\"",
                  "-",
                  "-",
                  "-",
                  "-",
                  "-",
                  "-",
                  "-",
                  "-"
                ],
                "output": "\"no hit\""
              },
              {
                "inputs": [
                  "\"Gemeentelijk monument\"",
                  "-",
                  "-",
                  "-",
                  "-",
                  "-",
                  "-",
                  "-",
                  "-"
                ],
                "output": "\"no hit\""
              },
              {
                "inputs": [
                  "-",
                  "\"Ik ga een nieuw kozijn plaatsen op een plek waar er eerst geen was.\"",
                  "-",
                  "-",
                  "-",
                  "-",
                  "-",
                  "-",
                  "-"
                ],
                "output": "\"no hit\""
              },
              {
                "inputs": [
                  "-",
                  "-",
                  "\"Nee, de vorm, de grootte en het profiel veranderen niet.\"",
                  "-",
                  "-",
                  "-",
                  "-",
                  "-",
                  "-"
                ],
                "output": "\"no hit\""
              },
              {
                "inputs": [
                  "-",
                  "-",
                  "-",
                  "\"Ja, het gebouw ligt in een gemeentelijk beschermd stads- of dorpsgezicht.\"",
                  "-",
                  "-",
                  "-",
                  "-",
                  "-"
                ],
                "output": "\"no hit\""
              },
              {
                "inputs": [
                  "-",
                  "-",
                  "-",
                  "\"Nee, het gebouw ligt niet in een beschermd stads- of dorpsgezicht.\"",
                  "-",
                  "-",
                  "-",
                  "-",
                  "-"
                ],
                "output": "\"no hit\""
              },
              {
                "inputs": [
                  "-",
                  "-",
                  "-",
                  "-",
                  "\"In een aanbouw, uitbouw of bijgebouw\"",
                  "-",
                  "-",
                  "-",
                  "-"
                ],
                "output": "\"no hit\""
              },
              {
                "inputs": [
                  "-",
                  "-",
                  "-",
                  "-",
                  "-",
                  "\"Voorkant\"",
                  "-",
                  "-",
                  "-"
                ],
                "output": "\"no hit\""
              },
              {
                "inputs": [
                  "-",
                  "-",
                  "-",
                  "-",
                  "-",
                  "\"Zijkant\"",
                  "-",
                  "-",
                  "-"
                ],
                "output": "\"no hit\""
              },
              {
                "inputs": ["-", "-", "-", "-", "-", "-", true, "-", "-"],
                "output": "\"no hit\""
              },
              {
                "inputs": ["-", "-", "-", "-", "-", "-", "-", true, "-"],
                "output": "\"no hit\""
              },
              {
                "inputs": ["-", "-", "-", "-", "-", "-", "-", "-", false],
                "output": "\"no hit\""
              }
            ]
          }
        },
        "00d1e7906e51462a560fed6950599bf1": {
          "requiredInputs": [
            "1eadce5a190e452699c0b7620386c2ac",
            "ab7ad575972c1cb19bffde2977c00c2b",
            "8b312e9536ed39e46c3c0ea6248cb709",
            "e3c7868ee0fd5e496855f3462fc029f7",
            "00e898edcd392d99fd044cc7556d1130",
            "d49ca838fb038c0ead04dbf81fef24c5",
            "c13ff0b1421c4e4c179244d584ae4c1f",
            "34fc5a5b84202066fa3e29c6946939c1",
            "3fe613f807f0a5ee93b535b6ac05f880"
          ],
          "decisionTable": {
            "rules": [
              {
                "inputs": [
                  "\"Geen monument\"",
                  "\"Ik ga een kozijn plaatsen of vernieuwen op een plek waar er eerst al een was.\"",
                  "\"Ja, de vorm, de grootte of het profiel verandert.\"",
                  "\"Ja, het gebouw ligt in een gemeentelijk beschermd stads- of dorpsgezicht.\"",
                  "\"In een hoofdgebouw\"",
                  "\"Zijkant\"",
                  false,
                  false,
                  true
                ],
                "output": "\"Vergunningplicht\""
              },
              {
                "inputs": [
                  "\"Geen monument\"",
                  "\"Ik ga een kozijn plaatsen of vernieuwen op een plek waar er eerst al een was.\"",
                  "\"Ja, de vorm, de grootte of het profiel verandert.\"",
                  "\"Nee, het gebouw ligt niet in een beschermd stads- of dorpsgezicht.\"",
                  "\"In een hoofdgebouw\"",
                  "\"Zijkant\"",
                  false,
                  false,
                  true
                ],
                "output": "\"Vergunningplicht\""
              },
              {
                "inputs": [
                  "\"Rijksmonument\"",
                  "-",
                  "-",
                  "-",
                  "-",
                  "-",
                  "-",
                  "-",
                  "-"
                ],
                "output": "\"no hit\""
              },
              {
                "inputs": [
                  "\"Gemeentelijk monument\"",
                  "-",
                  "-",
                  "-",
                  "-",
                  "-",
                  "-",
                  "-",
                  "-"
                ],
                "output": "\"no hit\""
              },
              {
                "inputs": [
                  "-",
                  "\"Ik ga een nieuw kozijn plaatsen op een plek waar er eerst geen was.\"",
                  "-",
                  "-",
                  "-",
                  "-",
                  "-",
                  "-",
                  "-"
                ],
                "output": "\"no hit\""
              },
              {
                "inputs": [
                  "-",
                  "-",
                  "\"Nee, de vorm, de grootte en het profiel veranderen niet.\"",
                  "-",
                  "-",
                  "-",
                  "-",
                  "-",
                  "-"
                ],
                "output": "\"no hit\""
              },
              {
                "inputs": [
                  "-",
                  "-",
                  "-",
                  "\"Ja, het gebouw ligt in een rijksbeschermd stads- of dorpsgezicht.\"",
                  "-",
                  "-",
                  "-",
                  "-",
                  "-"
                ],
                "output": "\"no hit\""
              },
              {
                "inputs": [
                  "-",
                  "-",
                  "-",
                  "-",
                  "\"In een aanbouw, uitbouw of bijgebouw\"",
                  "-",
                  "-",
                  "-",
                  "-"
                ],
                "output": "\"no hit\""
              },
              {
                "inputs": [
                  "-",
                  "-",
                  "-",
                  "-",
                  "-",
                  "\"Voorkant\"",
                  "-",
                  "-",
                  "-"
                ],
                "output": "\"no hit\""
              },
              {
                "inputs": [
                  "-",
                  "-",
                  "-",
                  "-",
                  "-",
                  "\"Achterkant\"",
                  "-",
                  "-",
                  "-"
                ],
                "output": "\"no hit\""
              },
              {
                "inputs": ["-", "-", "-", "-", "-", "-", true, "-", "-"],
                "output": "\"no hit\""
              },
              {
                "inputs": ["-", "-", "-", "-", "-", "-", "-", true, "-"],
                "output": "\"no hit\""
              },
              {
                "inputs": ["-", "-", "-", "-", "-", "-", "-", "-", false],
                "output": "\"no hit\""
              }
            ]
          }
        },
        "dummy": {
          "requiredDecisions": [
            "c99c17a6bdbc88fb569b386c334e22d1",
            "e76509c142b257650275507d47278569",
            "c53d216cc5f7dfdc4081f284fbbd5d2a",
            "f9dabc794c6c8958fdf8c65ca31dbd27",
            "90604cba0b2648875090de04ac9bdead",
            "4f33a93ea5bd5cc7c0efe5677e5d769f",
            "724f7957962a90c0e6293a631c5bca56",
            "2f8f7f86c790b26baab89a36ee0f27b3",
            "56a34f164e07f0a92732c4d2e2a09908",
            "27ab07c61477af40760e3fbb423bd0bc",
            "b33dbd97ca479280ce028aa10b71214a",
            "6fd9039462721cdbd8125a12b4f9b2f4",
            "557285192983e6c96e9aee8160823835",
            "8bdbd484130d64d341727787050f0373",
            "05798c198bb3a36ecd06f1dba165e5da",
            "81faae5f15e7912f51af1b8af730b4fc",
            "5fbf20134def73bb88295b2a4678b52c",
            "00d1e7906e51462a560fed6950599bf1"
          ],
          "decisionTable": {
            "rules": [
              {
                "inputs": [
                  "\"Vergunningplicht\"",
                  "-",
                  "-",
                  "-",
                  "-",
                  "-",
                  "-",
                  "-",
                  "-",
                  "-",
                  "-",
                  "-",
                  "-",
                  "-",
                  "-",
                  "-",
                  "-",
                  "-"
                ],
                "output": "\"Vergunningplicht\"",
                "description": "U hebt een vergunning nodig voor het onderdeel bouwen. U vraagt deze vergunning aan bij het landelijke omgevingsloket. Klik hiervoor op onderstaande knop."
              },
              {
                "inputs": [
                  "-",
                  "\"NeemContactOpMet\"",
                  "-",
                  "-",
                  "-",
                  "-",
                  "-",
                  "-",
                  "-",
                  "-",
                  "-",
                  "-",
                  "-",
                  "-",
                  "-",
                  "-",
                  "-",
                  "-"
                ],
                "output": "\"NeemContactOpMet\"",
                "description": "U gaat een kozijn plaatsen in een bijgebouw. De regels die daarvoor gelden zijn erg ingewikkeld en hangen ook af van het bestemmingsplan dat voor uw gebouw geldt. Bel daarom met de gemeente op [14 020](tel:14020), maandag tot en met vrijdag van 08.00 tot 18.00 uur."
              },
              {
                "inputs": [
                  "-",
                  "-",
                  "\"Vergunningplicht\"",
                  "-",
                  "-",
                  "-",
                  "-",
                  "-",
                  "-",
                  "-",
                  "-",
                  "-",
                  "-",
                  "-",
                  "-",
                  "-",
                  "-",
                  "-"
                ],
                "output": "\"Vergunningplicht\"",
                "description": "U hebt een vergunning nodig voor het onderdeel bouwen. U vraagt deze vergunning aan bij het landelijke omgevingsloket. Klik hiervoor op onderstaande knop."
              },
              {
                "inputs": [
                  "-",
                  "-",
                  "-",
                  "\"NeemContactOpMet\"",
                  "-",
                  "-",
                  "-",
                  "-",
                  "-",
                  "-",
                  "-",
                  "-",
                  "-",
                  "-",
                  "-",
                  "-",
                  "-",
                  "-"
                ],
                "output": "\"NeemContactOpMet\"",
                "description": "U gaat een kozijn plaatsen in een bijgebouw. De regels die daarvoor gelden zijn erg ingewikkeld en hangen ook af van het bestemmingsplan dat voor uw gebouw geldt. Bel daarom met de gemeente op [14 020](tel:14020), maandag tot en met vrijdag van 08.00 tot 18.00 uur."
              },
              {
                "inputs": [
                  "-",
                  "-",
                  "-",
                  "-",
                  "\"Vergunningplicht\"",
                  "-",
                  "-",
                  "-",
                  "-",
                  "-",
                  "-",
                  "-",
                  "-",
                  "-",
                  "-",
                  "-",
                  "-",
                  "-"
                ],
                "output": "\"Vergunningplicht\"",
                "description": "U hebt een vergunning nodig voor het onderdeel bouwen. U vraagt deze vergunning aan bij het landelijke omgevingsloket. Klik hiervoor op onderstaande knop."
              },
              {
                "inputs": [
                  "-",
                  "-",
                  "-",
                  "-",
                  "-",
                  "\"Vergunningplicht\"",
                  "-",
                  "-",
                  "-",
                  "-",
                  "-",
                  "-",
                  "-",
                  "-",
                  "-",
                  "-",
                  "-",
                  "-"
                ],
                "output": "\"Vergunningplicht\"",
                "description": "U hebt een vergunning nodig voor het onderdeel bouwen. U vraagt deze vergunning aan bij het landelijke omgevingsloket. Klik hiervoor op onderstaande knop."
              },
              {
                "inputs": [
                  "-",
                  "-",
                  "-",
                  "-",
                  "-",
                  "-",
                  "\"Vergunningplicht\"",
                  "-",
                  "-",
                  "-",
                  "-",
                  "-",
                  "-",
                  "-",
                  "-",
                  "-",
                  "-",
                  "-"
                ],
                "output": "\"Vergunningplicht\"",
                "description": "U hebt een vergunning nodig voor het onderdeel bouwen. U vraagt deze vergunning aan bij het landelijke omgevingsloket. Klik hiervoor op onderstaande knop."
              },
              {
                "inputs": [
                  "-",
                  "-",
                  "-",
                  "-",
                  "-",
                  "-",
                  "-",
                  "\"Vergunningplicht\"",
                  "-",
                  "-",
                  "-",
                  "-",
                  "-",
                  "-",
                  "-",
                  "-",
                  "-",
                  "-"
                ],
                "output": "\"Vergunningplicht\"",
                "description": "U hebt een vergunning nodig voor het onderdeel bouwen. U vraagt deze vergunning aan bij het landelijke omgevingsloket. Klik hiervoor op onderstaande knop."
              },
              {
                "inputs": [
                  "-",
                  "-",
                  "-",
                  "-",
                  "-",
                  "-",
                  "-",
                  "-",
                  "\"Vergunningplicht\"",
                  "-",
                  "-",
                  "-",
                  "-",
                  "-",
                  "-",
                  "-",
                  "-",
                  "-"
                ],
                "output": "\"Vergunningplicht\"",
                "description": "U hebt een vergunning nodig voor het onderdeel bouwen. U vraagt deze vergunning aan bij het landelijke omgevingsloket. Klik hiervoor op onderstaande knop."
              },
              {
                "inputs": [
                  "-",
                  "-",
                  "-",
                  "-",
                  "-",
                  "-",
                  "-",
                  "-",
                  "-",
                  "\"Vergunningplicht\"",
                  "-",
                  "-",
                  "-",
                  "-",
                  "-",
                  "-",
                  "-",
                  "-"
                ],
                "output": "\"Vergunningplicht\"",
                "description": "U hebt een vergunning nodig voor het onderdeel bouwen. U vraagt deze vergunning aan bij het landelijke omgevingsloket. Klik hiervoor op onderstaande knop."
              },
              {
                "inputs": [
                  "-",
                  "-",
                  "-",
                  "-",
                  "-",
                  "-",
                  "-",
                  "-",
                  "-",
                  "-",
                  "\"Vergunningplicht\"",
                  "-",
                  "-",
                  "-",
                  "-",
                  "-",
                  "-",
                  "-"
                ],
                "output": "\"Vergunningplicht\"",
                "description": "U hebt een vergunning nodig voor het onderdeel bouwen. U vraagt deze vergunning aan bij het landelijke omgevingsloket. Klik hiervoor op onderstaande knop."
              },
              {
                "inputs": [
                  "-",
                  "-",
                  "-",
                  "-",
                  "-",
                  "-",
                  "-",
                  "-",
                  "-",
                  "-",
                  "-",
                  "\"Vergunningplicht\"",
                  "-",
                  "-",
                  "-",
                  "-",
                  "-",
                  "-"
                ],
                "output": "\"Vergunningplicht\"",
                "description": "U hebt een vergunning nodig voor het onderdeel bouwen. U vraagt deze vergunning aan bij het landelijke omgevingsloket. Klik hiervoor op onderstaande knop."
              },
              {
                "inputs": [
                  "-",
                  "-",
                  "-",
                  "-",
                  "-",
                  "-",
                  "-",
                  "-",
                  "-",
                  "-",
                  "-",
                  "-",
                  "\"Vergunningplicht\"",
                  "-",
                  "-",
                  "-",
                  "-",
                  "-"
                ],
                "output": "\"Vergunningplicht\"",
                "description": "U hebt een vergunning nodig voor het onderdeel bouwen. U vraagt deze vergunning aan bij het landelijke omgevingsloket. Klik hiervoor op onderstaande knop."
              },
              {
                "inputs": [
                  "-",
                  "-",
                  "-",
                  "-",
                  "-",
                  "-",
                  "-",
                  "-",
                  "-",
                  "-",
                  "-",
                  "-",
                  "-",
                  "\"Vergunningplicht\"",
                  "-",
                  "-",
                  "-",
                  "-"
                ],
                "output": "\"Vergunningplicht\"",
                "description": "U hebt een vergunning nodig voor het onderdeel bouwen. U vraagt deze vergunning aan bij het landelijke omgevingsloket. Klik hiervoor op onderstaande knop."
              },
              {
                "inputs": [
                  "-",
                  "-",
                  "-",
                  "-",
                  "-",
                  "-",
                  "-",
                  "-",
                  "-",
                  "-",
                  "-",
                  "-",
                  "-",
                  "-",
                  "\"Vergunningplicht\"",
                  "-",
                  "-",
                  "-"
                ],
                "output": "\"Vergunningplicht\"",
                "description": "U hebt een vergunning nodig voor het onderdeel bouwen. U vraagt deze vergunning aan bij het landelijke omgevingsloket. Klik hiervoor op onderstaande knop."
              },
              {
                "inputs": [
                  "-",
                  "-",
                  "-",
                  "-",
                  "-",
                  "-",
                  "-",
                  "-",
                  "-",
                  "-",
                  "-",
                  "-",
                  "-",
                  "-",
                  "-",
                  "\"Vergunningplicht\"",
                  "-",
                  "-"
                ],
                "output": "\"Vergunningplicht\"",
                "description": "U hebt een vergunning nodig voor het onderdeel bouwen. U vraagt deze vergunning aan bij het landelijke omgevingsloket. Klik hiervoor op onderstaande knop."
              },
              {
                "inputs": [
                  "-",
                  "-",
                  "-",
                  "-",
                  "-",
                  "-",
                  "-",
                  "-",
                  "-",
                  "-",
                  "-",
                  "-",
                  "-",
                  "-",
                  "-",
                  "-",
                  "\"Vergunningplicht\"",
                  "-"
                ],
                "output": "\"Vergunningplicht\"",
                "description": "U hebt een vergunning nodig voor het onderdeel bouwen. U vraagt deze vergunning aan bij het landelijke omgevingsloket. Klik hiervoor op onderstaande knop."
              },
              {
                "inputs": [
                  "-",
                  "-",
                  "-",
                  "-",
                  "-",
                  "-",
                  "-",
                  "-",
                  "-",
                  "-",
                  "-",
                  "-",
                  "-",
                  "-",
                  "-",
                  "-",
                  "-",
                  "\"Vergunningplicht\""
                ],
                "output": "\"Vergunningplicht\"",
                "description": "U hebt een vergunning nodig voor het onderdeel bouwen. U vraagt deze vergunning aan bij het landelijke omgevingsloket. Klik hiervoor op onderstaande knop."
              },
              {
                "inputs": [
                  "\"no hit\"",
                  "\"no hit\"",
                  "\"no hit\"",
                  "\"no hit\"",
                  "\"no hit\"",
                  "\"no hit\"",
                  "\"no hit\"",
                  "\"no hit\"",
                  "\"no hit\"",
                  "\"no hit\"",
                  "\"no hit\"",
                  "\"no hit\"",
                  "\"no hit\"",
                  "\"no hit\"",
                  "\"no hit\"",
                  "\"no hit\"",
                  "\"no hit\"",
                  "\"no hit\""
                ],
                "output": "\"Toestemmingsvrij\"",
                "description": "U hebt geen vergunning nodig voor het plaatsen van het kozijn. Wél moet u op een aantal dingen letten voordat u gaat bouwen. Uw aannemer kan u daarbij helpen.\n\nDit is waar u verder op moet letten:\n\n*   U moet voldoen aan de eisen van het Bouwbesluit. In het Bouwbesluit staan ook eisen voor de brandveiligheid.\n*   U moet rekening houden met beschermde flora en fauna. Bijvoorbeeld een nest zwaluwen onder de dakpannen.\n\nDenk ook aan:\n\n*   Het plaatsen van een hijskraan of container op straat of het reserveren van een parkeervak.\n*   Het afvoeren van bouw- en sloopafval.\n*   Het risico dat u asbest tegenkomt.\n*   Het burenrecht. Denk hierbij bijvoorbeeld aan uitzicht op het terrein van de buren.\n*   De gevolgen van het plaatsen van een kozijn voor de WOZ-waarde van uw huis."
              }
            ]
          }
        }
      }
    }
  ],
  "slug": "kozijnen-plaatsen"
}
