{
  "permits": [
    {
      "version": 1,
      "name": "Conclusie [IN ONTWIKKELING] Aanbouw gebruiken",
      "questions": [
        {
          "text": "Gaat u de aanbouw bouwen achter een tussenpand?",
          "type": "boolean",
          "id": "uitv__92107c8a-c42a-4991-9b2f-641b1c4b593b",
          "prio": 10
        },
        {
          "text": "Wordt de aanbouw gebruikt voor dezelfde functie als het hoofdgebouw?",
          "description": "Dus als het hoofdgebouw de functie wonen heeft wordt dat ook de functie van de aanbouw.",
          "type": "boolean",
          "id": "uitv__71fce1ff-c6bf-4601-aedb-5581f1183cc5",
          "prio": 20
        },
        {
          "text": "Wordt de aanbouw dieper dan 2,5 m uit de achtergevel van het hoofdgebouw?",
          "description": "![2.5 meter](https://s3.eu-central-1.amazonaws.com/assets.vergunningen.info/images/aanbouw_recht.png)\n\n![2.5 meter](https://s3.eu-central-1.amazonaws.com/assets.vergunningen.info/images/infogrph_-__depijp___popup_diepte_van_de_aanbouw_--_versprongen.png)",
          "type": "boolean",
          "id": "uitv__895ee2a4-f282-4181-924c-b1880686ba98",
          "prio": 30
        },
        {
          "text": "Wordt de aanbouw hoger dan 5 m?",
          "type": "boolean",
          "id": "uitv__d819946c-59ec-42f5-8f45-fb0bc6b139d0",
          "prio": 40
        },
        {
          "text": "Wordt de aanbouw hoger dan 0,3m boven de scheidingsconstructie van de 2e bouwlaag?",
          "description": "![0,3 meter](https://s3.eu-central-1.amazonaws.com/assets.vergunningen.info/images/infogrph_-__max__0_3_m_hoger_dan_de_vloer_van_de_2e_bouwlaag.png)",
          "type": "boolean",
          "id": "uitv__6b3852b2-c047-4c0a-bac0-cb2f88002e3c",
          "prio": 50
        },
        {
          "text": "Wordt de aanbouw hoger dan het hoofdgebouw?",
          "type": "boolean",
          "id": "uitv__c084dabb-6af6-4b5b-afde-838582c7a45b",
          "prio": 60
        },
        {
          "text": "Gaat u met de aanbouw meer dan 50% van het perceel bebouwen dat binnen de bestemming &#39;tuin&#39;?",
          "type": "boolean",
          "id": "uitv__11eb9026-dee0-412c-96f4-689407b813ce",
          "prio": 70
        },
        {
          "text": "Krijgt de aanbouw een groen dak met een waterbergend vermogen van ten minste 60 mm?",
          "type": "boolean",
          "id": "uitv__041564fd-7ab5-45b5-b5bb-96d531af5846",
          "prio": 80
        }
      ],
      "decisions": {
        "_90c128fc-466d-48f5-b97f-9ae45a162802": {
          "requiredInputs": ["#input__92107c8a-c42a-4991-9b2f-641b1c4b593b"],
          "decisionTable": {
            "rules": [
              {
                "inputs": [false],
                "output": "\"Vergunningplicht\""
              },
              {
                "inputs": [true],
                "output": "\"no hit\""
              }
            ]
          }
        },
        "_56f38712-8617-460f-98ae-cd380b768910": {
          "requiredInputs": ["#input__71fce1ff-c6bf-4601-aedb-5581f1183cc5"],
          "decisionTable": {
            "rules": [
              {
                "inputs": [false],
                "output": "\"Vergunningplicht\""
              },
              {
                "inputs": [true],
                "output": "\"no hit\""
              }
            ]
          }
        },
        "_069aa81e-b234-4a92-8c97-50b9bb5c66df": {
          "requiredInputs": ["#input__895ee2a4-f282-4181-924c-b1880686ba98"],
          "decisionTable": {
            "rules": [
              {
                "inputs": [true],
                "output": "\"Vergunningplicht\""
              },
              {
                "inputs": [false],
                "output": "\"no hit\""
              }
            ]
          }
        },
        "_d0b3e8ca-807c-4fe4-844b-429fb77d834d": {
          "requiredInputs": ["#input__d819946c-59ec-42f5-8f45-fb0bc6b139d0"],
          "decisionTable": {
            "rules": [
              {
                "inputs": [true],
                "output": "\"Vergunningplicht\""
              },
              {
                "inputs": [false],
                "output": "\"no hit\""
              }
            ]
          }
        },
        "_ef1dd2c2-663c-4bba-8e1b-c4b6322f502e": {
          "requiredInputs": ["#input__6b3852b2-c047-4c0a-bac0-cb2f88002e3c"],
          "decisionTable": {
            "rules": [
              {
                "inputs": [true],
                "output": "\"Vergunningplicht\""
              },
              {
                "inputs": [false],
                "output": "\"no hit\""
              }
            ]
          }
        },
        "_de06fd14-83c4-4b52-a56a-10d4d21cb8ed": {
          "requiredInputs": ["#input__c084dabb-6af6-4b5b-afde-838582c7a45b"],
          "decisionTable": {
            "rules": [
              {
                "inputs": [true],
                "output": "\"Vergunningplicht\""
              },
              {
                "inputs": [false],
                "output": "\"no hit\""
              }
            ]
          }
        },
        "_47cfc11c-338a-44c6-a8d2-82b79a751c41": {
          "requiredInputs": ["#input__11eb9026-dee0-412c-96f4-689407b813ce"],
          "decisionTable": {
            "rules": [
              {
                "inputs": [true],
                "output": "\"Vergunningplicht\""
              },
              {
                "inputs": [false],
                "output": "\"no hit\""
              }
            ]
          }
        },
        "_b1f30132-f5a6-4081-8d46-a9fe4e332888": {
          "requiredInputs": ["#input__041564fd-7ab5-45b5-b5bb-96d531af5846"],
          "decisionTable": {
            "rules": [
              {
                "inputs": [false],
                "output": "\"Vergunningplicht\""
              },
              {
                "inputs": [true],
                "output": "\"no hit\""
              }
            ]
          }
        },
        "dummy": {
          "requiredDecisions": [
            "#_90c128fc-466d-48f5-b97f-9ae45a162802",
            "#_56f38712-8617-460f-98ae-cd380b768910",
            "#_069aa81e-b234-4a92-8c97-50b9bb5c66df",
            "#_d0b3e8ca-807c-4fe4-844b-429fb77d834d",
            "#_ef1dd2c2-663c-4bba-8e1b-c4b6322f502e",
            "#_de06fd14-83c4-4b52-a56a-10d4d21cb8ed",
            "#_47cfc11c-338a-44c6-a8d2-82b79a751c41",
            "#_b1f30132-f5a6-4081-8d46-a9fe4e332888"
          ],
          "decisionTable": {
            "rules": [
              {
                "inputs": [
                  "\"Vergunningplicht\"",
                  "-",
                  "-",
                  "-",
                  "-",
                  "-",
                  "-",
                  "-"
                ],
                "output": "\"Vergunningplicht\""
              },
              {
                "inputs": [
                  "-",
                  "\"Vergunningplicht\"",
                  "-",
                  "-",
                  "-",
                  "-",
                  "-",
                  "-"
                ],
                "output": "\"Vergunningplicht\""
              },
              {
                "inputs": [
                  "-",
                  "-",
                  "\"Vergunningplicht\"",
                  "-",
                  "-",
                  "-",
                  "-",
                  "-"
                ],
                "output": "\"Vergunningplicht\""
              },
              {
                "inputs": [
                  "-",
                  "-",
                  "-",
                  "\"Vergunningplicht\"",
                  "-",
                  "-",
                  "-",
                  "-"
                ],
                "output": "\"Vergunningplicht\""
              },
              {
                "inputs": [
                  "-",
                  "-",
                  "-",
                  "-",
                  "\"Vergunningplicht\"",
                  "-",
                  "-",
                  "-"
                ],
                "output": "\"Vergunningplicht\""
              },
              {
                "inputs": [
                  "-",
                  "-",
                  "-",
                  "-",
                  "-",
                  "\"Vergunningplicht\"",
                  "-",
                  "-"
                ],
                "output": "\"Vergunningplicht\""
              },
              {
                "inputs": [
                  "-",
                  "-",
                  "-",
                  "-",
                  "-",
                  "-",
                  "\"Vergunningplicht\"",
                  "-"
                ],
                "output": "\"Vergunningplicht\""
              },
              {
                "inputs": [
                  "-",
                  "-",
                  "-",
                  "-",
                  "-",
                  "-",
                  "-",
                  "\"Vergunningplicht\""
                ],
                "output": "\"Vergunningplicht\""
              },
              {
                "inputs": [
                  "\"no hit\"",
                  "\"no hit\"",
                  "\"no hit\"",
                  "\"no hit\"",
                  "\"no hit\"",
                  "\"no hit\"",
                  "\"no hit\"",
                  "\"no hit\""
                ],
                "output": "\"Toestemmingsvrij\"",
                "description": "U hoeft voor de activiteit gebruiken geen toestemming aan te vragen."
              }
            ]
          }
        }
      },
      "inputs": {
        "input__92107c8a-c42a-4991-9b2f-641b1c4b593b": {
          "href": "#uitv__92107c8a-c42a-4991-9b2f-641b1c4b593b",
          "type": "boolean"
        },
        "input__71fce1ff-c6bf-4601-aedb-5581f1183cc5": {
          "href": "#uitv__71fce1ff-c6bf-4601-aedb-5581f1183cc5",
          "type": "boolean"
        },
        "input__895ee2a4-f282-4181-924c-b1880686ba98": {
          "href": "#uitv__895ee2a4-f282-4181-924c-b1880686ba98",
          "type": "boolean"
        },
        "input__d819946c-59ec-42f5-8f45-fb0bc6b139d0": {
          "href": "#uitv__d819946c-59ec-42f5-8f45-fb0bc6b139d0",
          "type": "boolean"
        },
        "input__6b3852b2-c047-4c0a-bac0-cb2f88002e3c": {
          "href": "#uitv__6b3852b2-c047-4c0a-bac0-cb2f88002e3c",
          "type": "boolean"
        },
        "input__c084dabb-6af6-4b5b-afde-838582c7a45b": {
          "href": "#uitv__c084dabb-6af6-4b5b-afde-838582c7a45b",
          "type": "boolean"
        },
        "input__11eb9026-dee0-412c-96f4-689407b813ce": {
          "href": "#uitv__11eb9026-dee0-412c-96f4-689407b813ce",
          "type": "boolean"
        },
        "input__041564fd-7ab5-45b5-b5bb-96d531af5846": {
          "href": "#uitv__041564fd-7ab5-45b5-b5bb-96d531af5846",
          "type": "boolean"
        }
      }
    }
  ],
  "slug": "MtNRm9GhSkdPavHJa"
}
